AUTHORS
Changelog
LICENSE
MANIFEST.in
README
README.rst
setup.cfg
setup.py
cl/__init__.py
cl/actors.py
cl/agents.py
cl/common.py
cl/consumers.py
cl/exceptions.py
cl/log.py
cl/models.py
cl/pools.py
cl/presence.py
cl/results.py
cl/utils.py
cl.egg-info/PKG-INFO
cl.egg-info/SOURCES.txt
cl.egg-info/dependency_links.txt
cl.egg-info/entry_points.txt
cl.egg-info/not-zip-safe
cl.egg-info/requires.txt
cl.egg-info/top_level.txt
cl/bin/__init__.py
cl/bin/base.py
cl/bin/cl.py
examples/__init__.py
examples/distributed_cache.py
examples/hello.py
requirements/default.txt
requirements/pkgutils.txt
requirements/test.txt