Metadata-Version: 1.0
Name: cl
Version: 0.0.1
Summary: cl (pronounced cell) is an actor framework for Kombu
Home-page: http://github.com/ask/cl/
Author: Ask Solem
Author-email: ask@rabbitmq.com
License: UNKNOWN
Platform: any
Classifier: Development Status :: 3 - Alpha
Classifier: License :: OSI Approved :: BSD License
Classifier: Operating System :: OS Independent
Classifier: Programming Language :: Python
Classifier: Programming Language :: Python :: 3
Classifier: Programming Language :: Python :: 2.7
Classifier: Programming Language :: Python :: 2.6
Classifier: Intended Audience :: Developers
Classifier: Topic :: Communications
Classifier: Topic :: System :: Distributed Computing
Classifier: Topic :: System :: Networking
Classifier: Topic :: Software Development :: Libraries :: Python Modules
